shapeae/__init__.py
shapeae/_settings.py
shapeae/data_generator.py
shapeae/main.py
shapeae/metrics.py
shapeae/model.py
shapeae/run_train_script.py
shapeae/utils.py
shapeae-0.0.1.dist-info/METADATA
shapeae-0.0.1.dist-info/WHEEL
shapeae-0.0.1.dist-info/top_level.txt
shapeae-0.0.1.dist-info/RECORD
